bgral/__init__.py
bgral/core.py
bgral/style_transfer.py
gen_x/__init__.py
gen_x/core.py
bgral-0.2.0.dist-info/LICENSE
bgral-0.2.0.dist-info/METADATA
bgral-0.2.0.dist-info/WHEEL
bgral-0.2.0.dist-info/top_level.txt
bgral-0.2.0.dist-info/RECORD
