Metadata-Version: 2.1
Name: bgral
Version: 0.2.0
Summary: A Python library for video style transfer and utility functions
Home-page: https://github.com/bhavyagujral26/bgral
Author: Bhavya Gujral
Author-email: bhavya.gujral2608@gmail.com
License: MIT
Platform: UNKNOWN
Classifier: Programming Language :: Python :: 3
Classifier: License :: OSI Approved :: MIT License
Classifier: Operating System :: OS Independent
Classifier: Development Status :: 3 - Alpha
Classifier: Intended Audience :: Developers
Classifier: Topic :: Multimedia :: Video
Classifier: Topic :: Software Development :: Libraries
Requires-Python: >=3.6
License-File: LICENSE
Requires-Dist: opencv-python
Requires-Dist: pillow
Requires-Dist: tensorflow-hub
Requires-Dist: tensorflow (>=2.8.0)
